{
  "线条小狗": {
    "type": "image",
    "container": [
      {
        "icon": "<img src=\"https://fastly.jsdelivr.net/gh/willow-god/owo/linedog/linedog-不要.gif\">",
        "text": "linedog-不要"
      },
      {
        "icon": "<img src=\"https://fastly.jsdelivr.net/gh/willow-god/owo/linedog/linedog-写不完了.gif\">",
        "text": "linedog-写不完了"
      },
      {
        "icon": "<img src=\"https://fastly.jsdelivr.net/gh/willow-god/owo/linedog/linedog-准备.gif\">",
        "text": "linedog-准备"
      },
      {
        "icon": "<img src=\"https://fastly.jsdelivr.net/gh/willow-god/owo/linedog/linedog-加油.gif\">",
        "text": "linedog-加油"
      },
      {
        "icon": "<img src=\"https://fastly.jsdelivr.net/gh/willow-god/owo/linedog/linedog-呸.gif\">",
        "text": "linedog-呸"
      },
      {
        "icon": "<img src=\"https://fastly.jsdelivr.net/gh/willow-god/owo/linedog/linedog-哼.gif\">",
        "text": "linedog-哼"
      },
      {
        "icon": "<img src=\"https://fastly.jsdelivr.net/gh/willow-god/owo/linedog/linedog-喂.gif\">",
        "text": "linedog-喂"
      },
      {
        "icon": "<img src=\"https://fastly.jsdelivr.net/gh/willow-god/owo/linedog/linedog-好棒.gif\">",
        "text": "linedog-好棒"
      },
      {
        "icon": "<img src=\"https://fastly.jsdelivr.net/gh/willow-god/owo/linedog/linedog-好痛.gif\">",
        "text": "linedog-好痛"
      },
      {
        "icon": "<img src=\"https://fastly.jsdelivr.net/gh/willow-god/owo/linedog/linedog-好耶.gif\">",
        "text": "linedog-好耶"
      },
      {
        "icon": "<img src=\"https://fastly.jsdelivr.net/gh/willow-god/owo/linedog/linedog-威胁.gif\">",
        "text": "linedog-威胁"
      },
      {
        "icon": "<img src=\"https://fastly.jsdelivr.net/gh/willow-god/owo/linedog/linedog-完成.gif\">",
        "text": "linedog-完成"
      },
      {
        "icon": "<img src=\"https://fastly.jsdelivr.net/gh/willow-god/owo/linedog/linedog-寻找.gif\">",
        "text": "linedog-寻找"
      },
      {
        "icon": "<img src=\"https://fastly.jsdelivr.net/gh/willow-god/owo/linedog/linedog-庆祝.gif\">",
        "text": "linedog-庆祝"
      },
      {
        "icon": "<img src=\"https://fastly.jsdelivr.net/gh/willow-god/owo/linedog/linedog-开心.gif\">",
        "text": "linedog-开心"
      },
      {
        "icon": "<img src=\"https://fastly.jsdelivr.net/gh/willow-god/owo/linedog/linedog-惊.gif\">",
        "text": "linedog-惊"
      },
      {
        "icon": "<img src=\"https://fastly.jsdelivr.net/gh/willow-god/owo/linedog/linedog-惊讶.gif\">",
        "text": "linedog-惊讶"
      },
      {
        "icon": "<img src=\"https://fastly.jsdelivr.net/gh/willow-god/owo/linedog/linedog-惊讶2.gif\">",
        "text": "linedog-惊讶2"
      },
      {
        "icon": "<img src=\"https://fastly.jsdelivr.net/gh/willow-god/owo/linedog/linedog-打你.gif\">",
        "text": "linedog-打你"
      },
      {
        "icon": "<img src=\"https://fastly.jsdelivr.net/gh/willow-god/owo/linedog/linedog-打你2.gif\">",
        "text": "linedog-打你2"
      },
      {
        "icon": "<img src=\"https://fastly.jsdelivr.net/gh/willow-god/owo/linedog/linedog-指.gif\">",
        "text": "linedog-指"
      },
      {
        "icon": "<img src=\"https://fastly.jsdelivr.net/gh/willow-god/owo/linedog/linedog-探头.gif\">",
        "text": "linedog-探头"
      },
      {
        "icon": "<img src=\"https://fastly.jsdelivr.net/gh/willow-god/owo/linedog/linedog-摇摆.gif\">",
        "text": "linedog-摇摆"
      },
      {
        "icon": "<img src=\"https://fastly.jsdelivr.net/gh/willow-god/owo/linedog/linedog-摊手.gif\">",
        "text": "linedog-摊手"
      },
      {
        "icon": "<img src=\"https://fastly.jsdelivr.net/gh/willow-god/owo/linedog/linedog-晃脚脚.gif\">",
        "text": "linedog-晃脚脚"
      },
      {
        "icon": "<img src=\"https://fastly.jsdelivr.net/gh/willow-god/owo/linedog/linedog-期待.gif\">",
        "text": "linedog-期待"
      },
      {
        "icon": "<img src=\"https://fastly.jsdelivr.net/gh/willow-god/owo/linedog/linedog-来了.gif\">",
        "text": "linedog-来了"
      },
      {
        "icon": "<img src=\"https://fastly.jsdelivr.net/gh/willow-god/owo/linedog/linedog-歪头.gif\">",
        "text": "linedog-歪头"
      },
      {
        "icon": "<img src=\"https://fastly.jsdelivr.net/gh/willow-god/owo/linedog/linedog-沮丧.gif\">",
        "text": "linedog-沮丧"
      },
      {
        "icon": "<img src=\"https://fastly.jsdelivr.net/gh/willow-god/owo/linedog/linedog-画圈圈.gif\">",
        "text": "linedog-画圈圈"
      },
      {
        "icon": "<img src=\"https://fastly.jsdelivr.net/gh/willow-god/owo/linedog/linedog-略.gif\">",
        "text": "linedog-略"
      },
      {
        "icon": "<img src=\"https://fastly.jsdelivr.net/gh/willow-god/owo/linedog/linedog-盯.gif\">",
        "text": "linedog-盯"
      },
      {
        "icon": "<img src=\"https://fastly.jsdelivr.net/gh/willow-god/owo/linedog/linedog-看窗外1.gif\">",
        "text": "linedog-看窗外1"
      },
      {
        "icon": "<img src=\"https://fastly.jsdelivr.net/gh/willow-god/owo/linedog/linedog-看窗外2.gif\">",
        "text": "linedog-看窗外2"
      },
      {
        "icon": "<img src=\"https://fastly.jsdelivr.net/gh/willow-god/owo/linedog/linedog-紧张.gif\">",
        "text": "linedog-紧张"
      },
      {
        "icon": "<img src=\"https://fastly.jsdelivr.net/gh/willow-god/owo/linedog/linedog-翘脚脚.gif\">",
        "text": "linedog-翘脚脚"
      },
      {
        "icon": "<img src=\"https://fastly.jsdelivr.net/gh/willow-god/owo/linedog/linedog-谢谢.gif\">",
        "text": "linedog-谢谢"
      },
      {
        "icon": "<img src=\"https://fastly.jsdelivr.net/gh/willow-god/owo/linedog/linedog-转圈.gif\">",
        "text": "linedog-转圈"
      },
      {
        "icon": "<img src=\"https://fastly.jsdelivr.net/gh/willow-god/owo/linedog/linedog-送你花花.gif\">",
        "text": "linedog-送你花花"
      },
      {
        "icon": "<img src=\"https://fastly.jsdelivr.net/gh/willow-god/owo/linedog/linedog-难过.gif\">",
        "text": "linedog-难过"
      },
      {
        "icon": "<img src=\"https://fastly.jsdelivr.net/gh/willow-god/owo/linedog/linedog-震惊.gif\">",
        "text": "linedog-震惊"
      },
      {
        "icon": "<img src=\"https://fastly.jsdelivr.net/gh/willow-god/owo/linedog/linedog-非常好.gif\">",
        "text": "linedog-非常好"
      },
      {
        "icon": "<img src=\"https://fastly.jsdelivr.net/gh/willow-god/owo/linedog/linedog-颓废.gif\">",
        "text": "linedog-颓废"
      }
    ]
  }
}